SEQ_DETECTOR.v
module fsm (
    input x,
    clk,
    rst,
    output reg y
);
  reg [2:0] state;
  localparam s0 = 3'b000;
  localparam s1 = 3'b001;
  localparam s2 = 3'b010;
  localparam s3 = 3'b011;
  localparam s4 = 3'b100;

  always @(posedge clk) begin
    y <= 1'b0;

    if (rst) begin
      state <= s0;
    end else
      case (state)
        s0: begin
          if (x) state <= s1;
          else state <= s0;
        end
        s1: begin
          if (x) state <= s1;
          else state <= s2;
        end
        s2: begin
          if (x) state <= s3;
          else state <= s0;
        end
        s3: begin
          if (x) begin
            state <= s4;
            y <= 1'b1;
          end else state <= s2;

        end
        s4: begin
          if (x) state <= s1;
          else state <= s2;

        end

        default: state <= s0;
      endcase

  end

endmodule

SQ_tb.v
`timescale 1ns / 1ps

module fsm_tb;

  reg  x;
  reg  clk;
  reg  rst;

  wire y;

  fsm uut (
      .x  (x),
      .clk(clk),
      .rst(rst),
      .y  (y)
  );

  always #5 clk = ~clk;


  initial begin
    $dumpfile("fsm.vcd");
    $dumpvars(0, fsm_tb);
  end


  initial begin
    clk = 0;
    x   = 0;
    rst = 1;


    #10 rst = 0;


    #10 x = 1;
    #10 x = 0;
    #10 x = 1;
    #10 x = 1;

    #10 x = 0;
    #10 x = 1;
    #10 x = 0;
    #10 x = 1;
    #10 x = 1;

    #20;

    $finish;
  end

  initial begin
    $monitor("Time=%0t | rst=%b | x=%b | state=%b | y=%b", $time, rst, x, uut.state, y);
  end

endmodule

fsm.vcd
$date
	Wed Sep 30 18:51:45 2026
$end
$version
	Icarus Verilog
$end
$timescale
	1ps
$end
$scope module fsm_tb $end
$var wire 1 ! y $end
$var reg 1 " clk $end
$var reg 1 # rst $end
$var reg 1 $ x $end
$scope module uut $end
$var wire 1 " clk $end
$var wire 1 # rst $end
$var wire 1 $ x $end
$var parameter 3 % s0 $end
$var parameter 3 & s1 $end
$var parameter 3 ' s2 $end
$var parameter 3 ( s3 $end
$var parameter 3 ) s4 $end
$var reg 3 * state [2:0] $end
$var reg 1 ! y $end
$upscope $end
$upscope $end
$enddefinitions $end
$comment Show the parameter values. $end
$dumpall
b100 )
b11 (
b10 '
b1 &
b0 %
$end
#0
$dumpvars
bx *
0$
1#
0"
x!
$end
#5000
b0 *
0!
1"
#10000
0"
0#
#15000
1"
#20000
0"
1$
#25000
b1 *
1"
#30000
0"
0$
#35000
b10 *
1"
#40000
0"
1$
#45000
b11 *
1"
#50000
0"
#55000
1!
b100 *
1"
#60000
0"
0$
#65000
b10 *
0!
1"
#70000
0"
1$
#75000
b11 *
1"
#80000
0"
0$
#85000
b10 *
1"
#90000
0"
1$
#95000
b11 *
1"
#100000
0"
#105000
1!
b100 *
1"
#110000
0"
#115000
b1 *
0!
1"
